{
  "project_info": {
    "project_number": "640710962646",
    "project_id": "fira-mynotes",
    "storage_bucket": "fira-mynotes.appspot.com"
  },
  "client": [
    {
      "client_info": {
        "mobilesdk_app_id": "1:640710962646:android:00a8c0d576c74dc0a08877",
        "android_client_info": {
          "package_name": "com.fira.mynotes"
        }
      },
      "oauth_client": [
        {
          "client_id": "640710962646-qtb16qgvs3h1sb85ggklj4v1u5ik23b4.apps.googleusercontent.com",
          "client_type": 3
        }
      ],
      "api_key": [
        {
          "current_key": "AIzaSyAdmFP-gUVU4mKRGxATSRGXaIn3mgrz974"
        }
      ],
      "services": {
        "appinvite_service": {
          "other_platform_oauth_client": [
            {
              "client_id": "640710962646-qtb16qgvs3h1sb85ggklj4v1u5ik23b4.apps.googleusercontent.com",
              "client_type": 3
            },
            {
              "client_id": "640710962646-dml0ift4el1v98pt3c960od1sf1mbsiu.apps.googleusercontent.com",
              "client_type": 2,
              "ios_info": {
                "bundle_id": "com.fira.mynotes"
              }
            }
          ]
        }
      }
    }
  ],
  "configuration_version": "1"
}